app_store_icon_hunter/__init__.py
app_store_icon_hunter/api/__init__.py
app_store_icon_hunter/api/main.py
app_store_icon_hunter/cli/__init__.py
app_store_icon_hunter/cli/main.py
app_store_icon_hunter/core/__init__.py
app_store_icon_hunter/core/app_store.py
app_store_icon_hunter/core/downloader.py
app_store_icon_hunter/core/google_play.py
app_store_icon_hunter/utils/__init__.py
app_store_icon_hunter/utils/helpers.py
tests/__init__.py
tests/test_cli.py
tests/test_core.py
app_store_icon_hunter-2.0.0.dist-info/METADATA
app_store_icon_hunter-2.0.0.dist-info/WHEEL
app_store_icon_hunter-2.0.0.dist-info/entry_points.txt
app_store_icon_hunter-2.0.0.dist-info/top_level.txt
app_store_icon_hunter-2.0.0.dist-info/RECORD
