Metadata-Version: 2.4
Name: app-store-icon-hunter
Version: 2.0.0
Summary: A powerful CLI tool and API for searching apps and downloading icons from App Store and Google Play
Home-page: https://github.com/Garyku0/app-store-icon-hunter
Author: SU-KO KUO
Author-email: su@okuso.uk
Classifier: Development Status :: 4 - Beta
Classifier: Intended Audience :: Developers
Classifier: Operating System :: OS Independent
Classifier: Programming Language :: Python :: 3
Classifier: Programming Language :: Python :: 3.8
Classifier: Programming Language :: Python :: 3.9
Classifier: Programming Language :: Python :: 3.10
Classifier: Programming Language :: Python :: 3.11
Classifier: Programming Language :: Python :: 3.12
Requires-Python: >=3.8
Requires-Dist: click>=8.0.0
Requires-Dist: requests>=2.25.0
Requires-Dist: Pillow>=8.0.0
Requires-Dist: fastapi>=0.68.0
Requires-Dist: uvicorn>=0.15.0
Requires-Dist: aiohttp>=3.8.0
Requires-Dist: aiofiles>=0.8.0
Requires-Dist: python-multipart>=0.0.5
Requires-Dist: pydantic>=1.8.0
Provides-Extra: dev
Requires-Dist: pytest>=6.0; extra == "dev"
Requires-Dist: black>=21.0; extra == "dev"
Requires-Dist: flake8>=3.8; extra == "dev"
Requires-Dist: build>=0.7.0; extra == "dev"
Requires-Dist: twine>=3.0.0; extra == "dev"
Dynamic: author
Dynamic: author-email
Dynamic: classifier
Dynamic: description
Dynamic: description-content-type
Dynamic: home-page
Dynamic: provides-extra
Dynamic: requires-dist
Dynamic: requires-python
Dynamic: summary
